botosc/__init__.py
botosc/base.py
botosc/connector.py
botosc/mixin.py
botosc/model.py
botosc/utils.py
botosc_gen/__init__.py
botosc_gen/main.py
botosc-0.8.dist-info/LICENCE
botosc-0.8.dist-info/METADATA
botosc-0.8.dist-info/WHEEL
botosc-0.8.dist-info/entry_points.txt
botosc-0.8.dist-info/top_level.txt
botosc-0.8.dist-info/RECORD
