Metadata-Version: 2.1
Name: botosc
Version: 0.8
Summary: Get dataclass objects out of Outscale API
Home-page: 
Author: Aubustou
Author-email: survivalfr@yahoo.fr
License: MIT
Requires-Python: >=3.9
License-File: LICENCE
Requires-Dist: requests
Requires-Dist: apischema
Requires-Dist: pyYAML
Requires-Dist: osc-sdk
